{"status": "1", "sku_id": "0", "color": "", "image": [{"scale": "0.49", "maxWidth": 1000, "title": "Rolf Benz 8100.", "img_id": "853685", "brand": "德国 ROLF BENZ", "collectedNum": "0", "height": "594", "width": "1218", "href": "images/product/853685.JPG", "crawl_from": "www.rolf-benz.com", "is_master": "1", "logo": "https://image.izhangan.com/60ae168149d62da64ccf1b2edcbb08b4.jpg", "id": "1142119"}, {"scale": "0.49", "maxWidth": 1000, "title": "Rolf Benz 8100.", "img_id": "853689", "brand": "德国 ROLF BENZ", "collectedNum": "0", "height": "594", "width": "1218", "href": "images/product/853689.JPG", "crawl_from": "www.rolf-benz.com", "is_master": "0", "logo": "https://image.izhangan.com/60ae168149d62da64ccf1b2edcbb08b4.jpg", "id": "1142119"}, {"scale": "0.49", "maxWidth": 1000, "title": "Rolf Benz 8100.", "img_id": "853688", "brand": "德国 ROLF BENZ", "collectedNum": "0", "height": "594", "width": "1218", "href": "images/product/853688.JPG", "crawl_from": "www.rolf-benz.com", "is_master": "0", "logo": "https://image.izhangan.com/60ae168149d62da64ccf1b2edcbb08b4.jpg", "id": "1142119"}, {"scale": "0.49", "maxWidth": 1000, "title": "Rolf Benz 8100.", "img_id": "853687", "brand": "德国 ROLF BENZ", "collectedNum": "0", "height": "594", "width": "1218", "href": "images/product/853687.JPG", "crawl_from": "www.rolf-benz.com", "is_master": "0", "logo": "https://image.izhangan.com/60ae168149d62da64ccf1b2edcbb08b4.jpg", "id": "1142119"}, {"scale": "0.49", "maxWidth": 1000, "title": "Rolf Benz 8100.", "img_id": "853686", "brand": "德国 ROLF BENZ", "collectedNum": "0", "height": "594", "width": "1218", "href": "images/product/853686.JPG", "crawl_from": "www.rolf-benz.com", "is_master": "0", "logo": "https://image.izhangan.com/60ae168149d62da64ccf1b2edcbb08b4.jpg", "id": "1142119"}], "prod_id": "0", "brand_id": "460", "pic_url": "", "crawl_url": "http://www.rolf-benz.com/en_OC/furniture/coffee-tables/8100/", "size": ["暂无"], "category": {"cat_code": "dining-tables", "edit_user": "8784", "pic_exists": "2", "cat_name": "餐桌", "cat_sort": "91", "valid": "1", "edit_time": "2017-02-21 15:55:53", "title": "【餐桌】北欧_现代_简约_新中式_进口品牌_客厅_餐厅_实木_餐桌价格_餐桌图片_软装图片-掌案", "cat_position": "3", "cat_pid": "96", "cat_url": "dining-tables", "is_show": "1", "add_user": "0", "keywords": "餐桌,餐桌图片,餐桌价格,意大利餐桌,美国餐桌,北欧餐桌,德国餐桌,实木餐桌", "add_time": "2015-05-14 15:07:32", "cat_img": "category/dining-tables.png", "cat_desc": "", "id": "21", "description": "全球家居设计图库——掌案，提供2017年国内外最流行的餐桌图片大全，以及餐桌尺寸、高度等信息，餐桌图片专区每日更新高达数万张高清餐桌设计图片，是目前更新速度最快，质量最高的餐桌图片素材网。"}, "scale": "0.49", "user_id": "0", "is_favor": 0, "download_url": "", "id": "1142119", "collection_num": "0", "params": [{"param_name": "餐厅", "type_name": "空间", "param_type": "6", "id": "10122", "param_code": "canting"}, {"param_name": "现代", "type_name": "风格", "param_type": "2", "id": "10176", "param_code": "现代"}], "buy_url": "", "add_time": "2017-04-18 15:35:00", "type": "1", "brand": {"brand_place_ename": "germany", "edit_time": "2017-04-19 15:37:58", "prod_num": "83", "valid": "1", "tags": "德国品质,现代简约,沙发研发", "cover_img": "3c919e065df0e58397cef08722abbfad.jpg", "brand_logo": "60ae168149d62da64ccf1b2edcbb08b4.jpg", "edit_user": "0", "brand_ename": "ROLF BENZ", "is_for_za": "1", "brand_uri": "", "brand_code": "RLE", "add_user": "8710", "brand_desc": "成立于T964年，源自德国，是当今世界上著名的家具品牌之一。在整整的50年间ROLF BENZ都倾情致力于沙发的研制，和奔驰汽车一样具备德国的优良品质。", "brand_place": "德国", "add_time": "2017-04-15 14:09:33", "brand_intro": null, "id": "460", "is_for_otb": "0", "brand_cname": "ROLF BENZ"}, "sort": "664", "crawl_from": "www.rolf-benz.com", "price": "0.00", "material": "", "vendor_prod_id": "", "vendor_sku_id": "", "edit_user": "0", "add_user": "0", "desc": "Rolf Benz 8100.\\n【{“标题”：“罗尔夫苯8100。”、“降序”：“身高42厘米：100 x 70 cmplate：透明玻璃（ESG），旋转和高度可调。台座：Matt或高光泽漆中密度纤维板，在脚轮。支柱：Matt或高光镀铬。”} ]\\n", "can_buy": "0", "remark": null, "name": "Rolf Benz 8100.", "edit_time": "2017-07-03 08:35:06", "file_url": "https://image.izhangan.com/nest_1204fc9e789ee834.jpg", "view_num": "0", "book": {"folders": {"rows": [], "total": 0}}, "dominant_color": "#e7e8e7", "book_id": "0", "file_height": "594", "category_id": "21", "valid": "1", "related": [{"collection_num": 1688, "name": "Agra @it Table", "url": "https://image.izhangan.com/nest_6addf538eb240705.jpg", "file_url": "https://image.izhangan.com/nest_6addf538eb240705.jpg", "brand_ename": "Potocco", "height": "1000", "width": "1000", "brand_place_ename": "italy", "category_id": 21, "id": "17946", "category_name": "餐桌"}, {"collection_num": 972, "name": "Bowl Credenzia", "url": "https://image.izhangan.com/nest_4d70c273c41da62c.jpg", "file_url": "https://image.izhangan.com/nest_4d70c273c41da62c.jpg", "brand_ename": "Kare", "height": "1400", "width": "1400", "brand_place_ename": "germany", "category_id": 21, "id": "86440", "category_name": "餐桌"}, {"collection_num": 1352, "name": "Extra Large Double Gourd Turquoise", "url": "https://image.izhangan.com/nest_35dbd882761b0970.jpg", "file_url": "https://image.izhangan.com/nest_35dbd882761b0970.jpg", "brand_ename": "Barbara Cosgrove Lamps", "height": "1280", "width": "1280", "brand_place_ename": "america", "category_id": 21, "id": "66901", "category_name": "餐桌"}, {"collection_num": 630, "name": "Soho Luxe Three-Tiered Tall Chest", "url": "https://image.izhangan.com/nest_9b9afe7296a033a7.jpg", "file_url": "https://image.izhangan.com/nest_9b9afe7296a033a7.jpg", "brand_ename": "Bernhardt", "height": "2000", "width": "1495", "brand_place_ename": "america", "category_id": 21, "id": "23036", "category_name": "餐桌"}, {"collection_num": 908, "name": "MIA WH", "url": "https://image.izhangan.com/nest_216cb7cf96f945aa.jpg", "file_url": "https://image.izhangan.com/nest_216cb7cf96f945aa.jpg", "brand_ename": "Worlds Away", "height": "600", "width": "600", "brand_place_ename": "america", "category_id": 21, "id": "103461", "category_name": "餐桌"}, {"collection_num": 1261, "name": "Jiff", "url": "https://image.izhangan.com/nest_2b968cef8faf4b1b.jpg", "file_url": "https://image.izhangan.com/nest_2b968cef8faf4b1b.jpg", "brand_ename": "Flexform", "height": "608", "width": "810", "brand_place_ename": "italy", "category_id": 21, "id": "28466", "category_name": "餐桌"}, {"collection_num": 1210, "name": "Elysee Recliner", "url": "https://image.izhangan.com/nest_f2274f851c0f9356.jpg", "file_url": "https://image.izhangan.com/nest_f2274f851c0f9356.jpg", "brand_ename": "Bernhardt", "height": "2000", "width": "1946", "brand_place_ename": "america", "category_id": 21, "id": "22555", "category_name": "餐桌"}, {"collection_num": 1463, "name": "Guy Chaddock Collection Margate Pub Table CE0829", "url": "https://image.izhangan.com/nest_3b8eba154d1301ed.jpg", "file_url": "https://image.izhangan.com/nest_3b8eba154d1301ed.jpg", "brand_ename": "Chaddock", "height": "768", "width": "1024", "brand_place_ename": "america", "category_id": 21, "id": "1383576", "category_name": "餐桌"}, {"collection_num": 520, "name": "fairy tale", "url": "https://image.izhangan.com/nest_b48282658f0d2320.jpg", "file_url": "https://image.izhangan.com/nest_b48282658f0d2320.jpg", "brand_ename": "Deny Designs", "height": "2048", "width": "1366", "brand_place_ename": "america", "category_id": 21, "id": "70129", "category_name": "餐桌"}, {"collection_num": 1732, "name": "Offcut Side Table Natural", "url": "https://image.izhangan.com/nest_2070575acdc11b7b.jpg", "file_url": "https://image.izhangan.com/nest_2070575acdc11b7b.jpg", "brand_ename": "Tom Dixon", "height": "1200", "width": "1457", "brand_place_ename": "england", "category_id": 21, "id": "121863", "category_name": "餐桌"}, {"collection_num": 689, "name": "W33 2=1", "url": "https://image.izhangan.com/nest_c479ed4e92af57f9.jpg", "file_url": "https://image.izhangan.com/nest_c479ed4e92af57f9.jpg", "brand_ename": "Cassina", "height": "1032", "width": "2560", "brand_place_ename": "italy", "category_id": 21, "id": "9205", "category_name": "餐桌"}, {"collection_num": 1460, "name": "13089 - Beatty Cocktail Table", "url": "https://image.izhangan.com/nest_f3c7c4d2c3fb4402.jpg", "file_url": "https://image.izhangan.com/nest_f3c7c4d2c3fb4402.jpg", "brand_ename": "Emerson Bentley", "height": "400", "width": "400", "brand_place_ename": "america", "category_id": 21, "id": "99628", "category_name": "餐桌"}, {"collection_num": 1545, "name": "马里特", "url": "https://image.izhangan.com/nest_a2467c92da4e7e41.jpg", "file_url": "https://image.izhangan.com/nest_a2467c92da4e7e41.jpg", "brand_ename": "宜家", "height": "500", "width": "500", "brand_place_ename": "sweden", "category_id": 21, "id": "1407865", "category_name": "餐桌"}, {"collection_num": 1474, "name": "Elise Console Table", "url": "https://image.izhangan.com/nest_3132897dc0305afb.jpg", "file_url": "https://image.izhangan.com/nest_3132897dc0305afb.jpg", "brand_ename": "Lexington Home", "height": "901", "width": "1200", "brand_place_ename": "america", "category_id": 21, "id": "76789", "category_name": "餐桌"}, {"collection_num": 1451, "name": "Vintage Dining Table", "url": "https://image.izhangan.com/nest_88bcd994b02ed27c.jpg", "file_url": "https://image.izhangan.com/nest_88bcd994b02ed27c.jpg", "brand_ename": "John Richard", "height": "800", "width": "1000", "brand_place_ename": "america", "category_id": 21, "id": "1384957", "category_name": "餐桌"}, {"collection_num": 1036, "name": "silverado chrome 80\" rectangular dining table", "url": "https://image.izhangan.com/nest_b609d0bc92f2eee1.jpg", "file_url": "https://image.izhangan.com/nest_b609d0bc92f2eee1.jpg", "brand_ename": "Cb2", "height": "800", "width": "800", "brand_place_ename": "america", "category_id": 21, "id": "1061", "category_name": "餐桌"}, {"collection_num": 1583, "name": "Neoclassical Pedestal Table", "url": "https://image.izhangan.com/nest_9b0f456d9db7e790.jpg", "file_url": "https://image.izhangan.com/nest_9b0f456d9db7e790.jpg", "brand_ename": "Restoration Hardware", "height": "1170", "width": "1200", "brand_place_ename": "america", "category_id": 21, "id": "573622", "category_name": "餐桌"}, {"collection_num": 951, "name": "ATELIER", "url": "https://image.izhangan.com/nest_de66d096bd434fad.jpg", "file_url": "https://image.izhangan.com/nest_de66d096bd434fad.jpg", "brand_ename": "Calligaris", "height": "1280", "width": "1600", "brand_place_ename": "italy", "category_id": 21, "id": "9497", "category_name": "餐桌"}, {"collection_num": 1146, "name": "French Urn Pedestal Round Dining Table", "url": "https://image.izhangan.com/nest_b70572ff45c5a440.jpg", "file_url": "https://image.izhangan.com/nest_b70572ff45c5a440.jpg", "brand_ename": "Restoration Hardware", "height": "1170", "width": "1200", "brand_place_ename": "america", "category_id": 21, "id": "573614", "category_name": "餐桌"}, {"collection_num": 847, "name": "blox 35x63 dining table", "url": "https://image.izhangan.com/nest_26996cf3c39bd455.jpg", "file_url": "https://image.izhangan.com/nest_26996cf3c39bd455.jpg", "brand_ename": "Cb2", "height": "800", "width": "800", "brand_place_ename": "america", "category_id": 21, "id": "1074", "category_name": "餐桌"}, {"collection_num": 950, "name": "456 PANTHEON", "url": "https://image.izhangan.com/nest_712a991e1a7599eb.jpg", "file_url": "https://image.izhangan.com/nest_712a991e1a7599eb.jpg", "brand_ename": "Cassina", "height": "1032", "width": "2560", "brand_place_ename": "italy", "category_id": 21, "id": "9182", "category_name": "餐桌"}, {"collection_num": 944, "name": "Extensible rectangular table 160+50x90", "url": "https://image.izhangan.com/nest_465c270b83e1c92b.jpg", "file_url": "https://image.izhangan.com/nest_465c270b83e1c92b.jpg", "brand_ename": "emu", "height": "1700", "width": "2000", "brand_place_ename": "italy", "category_id": 21, "id": "92247", "category_name": "餐桌"}, {"collection_num": 1360, "name": "19th C. French Acanthus Brasserie Table", "url": "https://image.izhangan.com/nest_88c58704acf2fe08.jpg", "file_url": "https://image.izhangan.com/nest_88c58704acf2fe08.jpg", "brand_ename": "Restoration Hardware", "height": "1170", "width": "1200", "brand_place_ename": "america", "category_id": 21, "id": "573626", "category_name": "餐桌"}, {"collection_num": 1290, "name": "米比", "url": "https://image.izhangan.com/nest_f578f341c851db7f.jpg", "file_url": "https://image.izhangan.com/nest_f578f341c851db7f.jpg", "brand_ename": "宜家", "height": "500", "width": "500", "brand_place_ename": "sweden", "category_id": 21, "id": "1407842", "category_name": "餐桌"}, {"collection_num": 1005, "name": "12152 - Canton End Table", "url": "https://image.izhangan.com/nest_f5086ab2c0bd589d.jpg", "file_url": "https://image.izhangan.com/nest_f5086ab2c0bd589d.jpg", "brand_ename": "Emerson Bentley", "height": "400", "width": "400", "brand_place_ename": "america", "category_id": 21, "id": "99612", "category_name": "餐桌"}, {"collection_num": 1286, "name": "Flatiron Round Dining Table", "url": "https://image.izhangan.com/nest_edf0dc13e083da32.jpg", "file_url": "https://image.izhangan.com/nest_edf0dc13e083da32.jpg", "brand_ename": "Restoration Hardware", "height": "1170", "width": "1200", "brand_place_ename": "america", "category_id": 21, "id": "573586", "category_name": "餐桌"}, {"collection_num": 1380, "name": "Coffee Table Tronco", "url": "https://image.izhangan.com/nest_82fab43242a9727d.jpg", "file_url": "https://image.izhangan.com/nest_82fab43242a9727d.jpg", "brand_ename": "Kare", "height": "1400", "width": "1400", "brand_place_ename": "germany", "category_id": 21, "id": "82930", "category_name": "餐桌"}, {"collection_num": 1500, "name": "Larkspur Coffee Table", "url": "https://image.izhangan.com/nest_aee8bdf490d74107.jpg", "file_url": "https://image.izhangan.com/nest_aee8bdf490d74107.jpg", "brand_ename": "Restoration Hardware", "height": "1170", "width": "1200", "brand_place_ename": "america", "category_id": 21, "id": "561718", "category_name": "餐桌"}, {"collection_num": 1250, "name": "EZRA DINING TABLE - 94.5\"", "url": "https://image.izhangan.com/nest_6d02322b0b166e8e.jpg", "file_url": "https://image.izhangan.com/nest_6d02322b0b166e8e.jpg", "brand_ename": "Sunpan", "height": "800", "width": "1000", "brand_place_ename": "america", "category_id": 21, "id": "100847", "category_name": "餐桌"}, {"collection_num": 1410, "name": "fellow fawn", "url": "https://image.izhangan.com/nest_c1527f7449754bf6.jpg", "file_url": "https://image.izhangan.com/nest_c1527f7449754bf6.jpg", "brand_ename": "Deny Designs", "height": "2048", "width": "1366", "brand_place_ename": "america", "category_id": 21, "id": "68858", "category_name": "餐桌"}, {"collection_num": 1154, "name": "查尔丝汀沙发桌", "url": "https://image.izhangan.com/nest_c6665a07031eac16.jpg", "file_url": "https://image.izhangan.com/nest_c6665a07031eac16.jpg", "brand_ename": "美克美家", "height": "514", "width": "720", "brand_place_ename": "china", "category_id": 21, "id": "1400187", "category_name": "餐桌"}, {"collection_num": 854, "name": "Side Table Sceptre", "url": "https://image.izhangan.com/nest_07b96eca9249e209.jpg", "file_url": "https://image.izhangan.com/nest_07b96eca9249e209.jpg", "brand_ename": "Eichholtz", "height": "1024", "width": "1024", "brand_place_ename": "netherlands", "category_id": 21, "id": "96056", "category_name": "餐桌"}, {"collection_num": 839, "name": "塞纳之光咖啡桌", "url": "https://image.izhangan.com/nest_1655e5d7c35dd979.jpg", "file_url": "https://image.izhangan.com/nest_1655e5d7c35dd979.jpg", "brand_ename": "美克美家", "height": "514", "width": "720", "brand_place_ename": "china", "category_id": 21, "id": "1400183", "category_name": "餐桌"}, {"collection_num": 1157, "name": "Cantor Sectional", "url": "https://image.izhangan.com/nest_2552ccb2218f54db.jpg", "file_url": "https://image.izhangan.com/nest_2552ccb2218f54db.jpg", "brand_ename": "Bernhardt", "height": "763", "width": "2000", "brand_place_ename": "america", "category_id": 21, "id": "22361", "category_name": "餐桌"}, {"collection_num": 1499, "name": "PAN", "url": "https://image.izhangan.com/nest_c4573cf5645083b6.jpg", "file_url": "https://image.izhangan.com/nest_c4573cf5645083b6.jpg", "brand_ename": "Cappellini", "height": "870", "width": "1280", "brand_place_ename": "italy", "category_id": 21, "id": "10861", "category_name": "餐桌"}, {"collection_num": 1203, "name": "modern peach roses", "url": "https://image.izhangan.com/nest_92a8e6786ce32abb.jpg", "file_url": "https://image.izhangan.com/nest_92a8e6786ce32abb.jpg", "brand_ename": "Deny Designs", "height": "2048", "width": "1366", "brand_place_ename": "america", "category_id": 21, "id": "33346", "category_name": "餐桌"}], "file_width": "1218"}