{"status": "1", "sku_id": "0", "color": "", "image": [{"scale": "0.55", "maxWidth": 1000, "title": "Ventura", "img_id": "137014", "brand": "意大利 Poliform", "collectedNum": "0", "height": "660", "width": "1200", "href": "images/product/137014.JPG", "crawl_from": "www.poliform.it", "is_master": "1", "logo": "https://image.izhangan.com/PFM.jpg", "id": "15928"}, {"scale": "1.42", "maxWidth": 1000, "title": "Ventura", "img_id": "137033", "brand": "意大利 Poliform", "collectedNum": "0", "height": "765", "width": "539", "href": "images/product/137033.JPG", "crawl_from": "www.poliform.it", "is_master": "0", "logo": "https://image.izhangan.com/PFM.jpg", "id": "15928"}, {"scale": "1.24", "maxWidth": 1000, "title": "Ventura", "img_id": "137032", "brand": "意大利 Poliform", "collectedNum": "0", "height": "765", "width": "619", "href": "images/product/137032.JPG", "crawl_from": "www.poliform.it", "is_master": "0", "logo": "https://image.izhangan.com/PFM.jpg", "id": "15928"}, {"scale": "1.11", "maxWidth": 1000, "title": "Ventura", "img_id": "137031", "brand": "意大利 Poliform", "collectedNum": "0", "height": "765", "width": "687", "href": "images/product/137031.JPG", "crawl_from": "www.poliform.it", "is_master": "0", "logo": "https://image.izhangan.com/PFM.jpg", "id": "15928"}, {"scale": "1.28", "maxWidth": 1000, "title": "Ventura", "img_id": "137030", "brand": "意大利 Poliform", "collectedNum": "0", "height": "765", "width": "597", "href": "images/product/137030.JPG", "crawl_from": "www.poliform.it", "is_master": "0", "logo": "https://image.izhangan.com/PFM.jpg", "id": "15928"}, {"scale": "1.24", "maxWidth": 1000, "title": "Ventura", "img_id": "137029", "brand": "意大利 Poliform", "collectedNum": "0", "height": "765", "width": "617", "href": "images/product/137029.JPG", "crawl_from": "www.poliform.it", "is_master": "0", "logo": "https://image.izhangan.com/PFM.jpg", "id": "15928"}, {"scale": "1.22", "maxWidth": 1000, "title": "Ventura", "img_id": "137028", "brand": "意大利 Poliform", "collectedNum": "0", "height": "765", "width": "626", "href": "images/product/137028.JPG", "crawl_from": "www.poliform.it", "is_master": "0", "logo": "https://image.izhangan.com/PFM.jpg", "id": "15928"}, {"scale": "0.64", "maxWidth": 1000, "title": "Ventura", "img_id": "137027", "brand": "意大利 Poliform", "collectedNum": "0", "height": "765", "width": "1200", "href": "images/product/137027.JPG", "crawl_from": "www.poliform.it", "is_master": "0", "logo": "https://image.izhangan.com/PFM.jpg", "id": "15928"}, {"scale": "0.64", "maxWidth": 1000, "title": "Ventura", "img_id": "137026", "brand": "意大利 Poliform", "collectedNum": "0", "height": "765", "width": "1200", "href": "images/product/137026.JPG", "crawl_from": "www.poliform.it", "is_master": "0", "logo": "https://image.izhangan.com/PFM.jpg", "id": "15928"}, {"scale": "0.41", "maxWidth": 1000, "title": "Ventura", "img_id": "137025", "brand": "意大利 Poliform", "collectedNum": "0", "height": "489", "width": "1200", "href": "images/product/137025.JPG", "crawl_from": "www.poliform.it", "is_master": "0", "logo": "https://image.izhangan.com/PFM.jpg", "id": "15928"}, {"scale": "1.00", "maxWidth": 1000, "title": "Ventura", "img_id": "137024", "brand": "意大利 Poliform", "collectedNum": "0", "height": "765", "width": "765", "href": "images/product/137024.JPG", "crawl_from": "www.poliform.it", "is_master": "0", "logo": "https://image.izhangan.com/PFM.jpg", "id": "15928"}, {"scale": "1.00", "maxWidth": 1000, "title": "Ventura", "img_id": "137023", "brand": "意大利 Poliform", "collectedNum": "0", "height": "765", "width": "765", "href": "images/product/137023.JPG", "crawl_from": "www.poliform.it", "is_master": "0", "logo": "https://image.izhangan.com/PFM.jpg", "id": "15928"}, {"scale": "1.00", "maxWidth": 1000, "title": "Ventura", "img_id": "137022", "brand": "意大利 Poliform", "collectedNum": "0", "height": "765", "width": "765", "href": "images/product/137022.JPG", "crawl_from": "www.poliform.it", "is_master": "0", "logo": "https://image.izhangan.com/PFM.jpg", "id": "15928"}, {"scale": "1.00", "maxWidth": 1000, "title": "Ventura", "img_id": "137021", "brand": "意大利 Poliform", "collectedNum": "0", "height": "765", "width": "765", "href": "images/product/137021.JPG", "crawl_from": "www.poliform.it", "is_master": "0", "logo": "https://image.izhangan.com/PFM.jpg", "id": "15928"}, {"scale": "1.18", "maxWidth": 1000, "title": "Ventura", "img_id": "137020", "brand": "意大利 Poliform", "collectedNum": "0", "height": "765", "width": "650", "href": "images/product/137020.JPG", "crawl_from": "www.poliform.it", "is_master": "0", "logo": "https://image.izhangan.com/PFM.jpg", "id": "15928"}, {"scale": "0.64", "maxWidth": 1000, "title": "Ventura", "img_id": "137019", "brand": "意大利 Poliform", "collectedNum": "0", "height": "765", "width": "1200", "href": "images/product/137019.JPG", "crawl_from": "www.poliform.it", "is_master": "0", "logo": "https://image.izhangan.com/PFM.jpg", "id": "15928"}, {"scale": "1.26", "maxWidth": 1000, "title": "Ventura", "img_id": "137018", "brand": "意大利 Poliform", "collectedNum": "0", "height": "765", "width": "609", "href": "images/product/137018.JPG", "crawl_from": "www.poliform.it", "is_master": "0", "logo": "https://image.izhangan.com/PFM.jpg", "id": "15928"}, {"scale": "1.43", "maxWidth": 1000, "title": "Ventura", "img_id": "137017", "brand": "意大利 Poliform", "collectedNum": "0", "height": "765", "width": "536", "href": "images/product/137017.JPG", "crawl_from": "www.poliform.it", "is_master": "0", "logo": "https://image.izhangan.com/PFM.jpg", "id": "15928"}, {"scale": "0.64", "maxWidth": 1000, "title": "Ventura", "img_id": "137016", "brand": "意大利 Poliform", "collectedNum": "0", "height": "765", "width": "1200", "href": "images/product/137016.JPG", "crawl_from": "www.poliform.it", "is_master": "0", "logo": "https://image.izhangan.com/PFM.jpg", "id": "15928"}, {"scale": "1.25", "maxWidth": 1000, "title": "Ventura", "img_id": "137015", "brand": "意大利 Poliform", "collectedNum": "0", "height": "765", "width": "612", "href": "images/product/137015.JPG", "crawl_from": "www.poliform.it", "is_master": "0", "logo": "https://image.izhangan.com/PFM.jpg", "id": "15928"}], "prod_id": "0", "brand_id": "257", "pic_url": "", "crawl_url": "http://www.poliform.it/it/prodotti/poliform/sedie/ventura", "size": ["暂无"], "category": {"cat_code": "chairs-chaises", "edit_user": "8784", "pic_exists": "2", "cat_name": "椅", "cat_sort": "89", "valid": "1", "edit_time": "2017-02-21 16:16:24", "title": "【椅子】北欧_现代_简约_新中式_进口品牌_客厅_书房_卧室_餐厅_花园_椅子价格_椅子图片_软装图片-掌案", "cat_position": "3", "cat_pid": "97", "cat_url": "chair-chaises", "is_show": "1", "add_user": "0", "keywords": "椅子,椅子图片,椅子价格,意大利椅子,美国椅子,北欧椅子,德国椅子", "add_time": "2015-05-14 15:07:38", "cat_img": "category/chairs-chaises.png", "cat_desc": "", "id": "33", "description": "全球家居设计图库——掌案，提供2017年国内外最流行的椅子图片大全，以及椅子尺寸、高度等信息，椅子图片专区每日更新高达数万张高清椅子设计图片，是目前更新速度最快，质量最高的椅子图片素材网。"}, "scale": "0.55", "user_id": "0", "is_favor": 0, "download_url": "", "id": "15928", "collection_num": "0", "params": [{"param_name": "客厅", "type_name": "空间", "param_type": "6", "id": "10121", "param_code": "keting"}, {"param_name": "餐厅", "type_name": "空间", "param_type": "6", "id": "10122", "param_code": "canting"}, {"param_name": "书房", "type_name": "空间", "param_type": "6", "id": "10125", "param_code": "shufang"}, {"param_name": "现代", "type_name": "风格", "param_type": "2", "id": "10176", "param_code": "现代"}], "buy_url": "", "add_time": "2017-01-20 11:39:10", "type": "1", "brand": {"brand_place_ename": "italy", "edit_time": "2017-03-01 13:57:16", "prod_num": "135", "valid": "1", "tags": "厨房美学,意式奢华,现代前卫", "cover_img": "nest_731cbc794105be68.jpg", "brand_logo": "PFM.jpg", "edit_user": "8710", "brand_ename": "Poliform", "is_for_za": "1", "brand_uri": "poliform", "brand_code": "PFM", "add_user": "8693", "brand_desc": "Poliform拥有50多年的历史，对于世界家具设计有着传奇般的突出贡献。源自家族经营的小型艺术工作室，将对卓越品质的无止尽追求融于悠久的木造传统手工艺之中，注重心灵感受和需求。", "brand_place": "意大利", "add_time": "2017-01-20 09:56:14", "brand_intro": null, "id": "257", "is_for_otb": "1", "brand_cname": "Poliform"}, "sort": "975", "crawl_from": "www.poliform.it", "price": "0.00", "material": "", "vendor_prod_id": "", "vendor_sku_id": "", "edit_user": "0", "add_user": "0", "desc": "", "can_buy": "0", "remark": "", "name": "Ventura", "edit_time": "2017-06-29 07:01:31", "file_url": "https://image.izhangan.com/nest_ef8a4bd9b837681a.jpg", "view_num": "0", "book": {"folders": {"rows": [], "total": 0}}, "dominant_color": "#74706d", "book_id": "0", "file_height": "660", "category_id": "33", "valid": "1", "related": [{"collection_num": 1109, "name": "Fire Side Plinth Chair", "url": "https://image.izhangan.com/nest_80285ff6828443b4.jpg", "file_url": "https://image.izhangan.com/nest_80285ff6828443b4.jpg", "brand_ename": "Kagan", "height": "490", "width": "660", "brand_place_ename": "italy", "category_id": 33, "id": "10255", "category_name": "椅"}, {"collection_num": 935, "name": "Dolly", "url": "https://image.izhangan.com/nest_8c939697ea1d72cb.jpg", "file_url": "https://image.izhangan.com/nest_8c939697ea1d72cb.jpg", "brand_ename": "Natuzzi", "height": "1080", "width": "1920", "brand_place_ename": "italy", "category_id": 33, "id": "11523", "category_name": "椅"}, {"collection_num": 1664, "name": "靠背椅", "url": "https://image.izhangan.com/kaobeiyi_54bcf7100.jpg", "file_url": "https://image.izhangan.com/kaobeiyi_54bcf7100.jpg", "brand_ename": "Palecek", "height": "595", "width": "700", "brand_place_ename": "america", "category_id": 33, "id": "4884", "category_name": "椅"}, {"collection_num": 1044, "name": "Contour High Back Lounge", "url": "https://image.izhangan.com/nest_dd08219ab7701af3.jpg", "file_url": "https://image.izhangan.com/nest_dd08219ab7701af3.jpg", "brand_ename": "Kagan", "height": "490", "width": "660", "brand_place_ename": "italy", "category_id": 33, "id": "10231", "category_name": "椅"}, {"collection_num": 995, "name": "Flying Carpet", "url": "https://image.izhangan.com/nest_75b2a83a4229213f.jpg", "file_url": "https://image.izhangan.com/nest_75b2a83a4229213f.jpg", "brand_ename": "Magis", "height": "1539", "width": "2583", "brand_place_ename": "italy", "category_id": 33, "id": "14097", "category_name": "椅"}, {"collection_num": 1552, "name": "Magis Paso Doble Chair", "url": "https://image.izhangan.com/nest_b389e6ecf3db9336.jpg", "file_url": "https://image.izhangan.com/nest_b389e6ecf3db9336.jpg", "brand_ename": "HermanMiller", "height": "480", "width": "1200", "brand_place_ename": "america", "category_id": 33, "id": "18665", "category_name": "椅"}, {"collection_num": 1102, "name": "Palma", "url": "https://image.izhangan.com/nest_6e271c193fae28fc.jpg", "file_url": "https://image.izhangan.com/nest_6e271c193fae28fc.jpg", "brand_ename": "Offecct", "height": "647", "width": "970", "brand_place_ename": "sweden", "category_id": 33, "id": "11352", "category_name": "椅"}, {"collection_num": 1141, "name": "Fettuccini Chair", "url": "https://image.izhangan.com/nest_834b379120660c44.jpg", "file_url": "https://image.izhangan.com/nest_834b379120660c44.jpg", "brand_ename": "Kagan", "height": "490", "width": "660", "brand_place_ename": "italy", "category_id": 33, "id": "10243", "category_name": "椅"}, {"collection_num": 1519, "name": "Grace Lounge", "url": "https://image.izhangan.com/nest_d068c2c1a004dbea.jpg", "file_url": "https://image.izhangan.com/nest_d068c2c1a004dbea.jpg", "brand_ename": "Potocco", "height": "1000", "width": "1000", "brand_place_ename": "italy", "category_id": 33, "id": "17758", "category_name": "椅"}, {"collection_num": 1194, "name": "Bumper Chair", "url": "https://image.izhangan.com/nest_6fab1471d55277bf.jpg", "file_url": "https://image.izhangan.com/nest_6fab1471d55277bf.jpg", "brand_ename": "HermanMiller", "height": "540", "width": "800", "brand_place_ename": "america", "category_id": 33, "id": "18513", "category_name": "椅"}, {"collection_num": 1602, "name": "Pato Veneer Office Armchair", "url": "https://image.izhangan.com/nest_90cc46ed96fdb4ea.jpg", "file_url": "https://image.izhangan.com/nest_90cc46ed96fdb4ea.jpg", "brand_ename": "Fredericia", "height": "675", "width": "1218", "brand_place_ename": "danmark", "category_id": 33, "id": "9969", "category_name": "椅"}, {"collection_num": 1249, "name": "SIGNE(シグネ)　スツール　ナチュラル脚", "url": "https://image.izhangan.com/nest_11cb52756455e7ab.jpg", "file_url": "https://image.izhangan.com/nest_11cb52756455e7ab.jpg", "brand_ename": "Unico", "height": "494", "width": "728", "brand_place_ename": "japan", "category_id": 33, "id": "16434", "category_name": "椅"}, {"collection_num": 1659, "name": "LOTUS (LOW MEDIUM HIGH)", "url": "https://image.izhangan.com/nest_c5aabc6df1e522b5.jpg", "file_url": "https://image.izhangan.com/nest_c5aabc6df1e522b5.jpg", "brand_ename": "Cappellini", "height": "961", "width": "1280", "brand_place_ename": "italy", "category_id": 33, "id": "10786", "category_name": "椅"}, {"collection_num": 469, "name": "10 VAGUES", "url": "https://image.izhangan.com/nest_e06b8ea31faabb82.jpg", "file_url": "https://image.izhangan.com/nest_e06b8ea31faabb82.jpg", "brand_ename": "Ligne Roset", "height": "1848", "width": "1848", "brand_place_ename": "france", "category_id": 33, "id": "12033", "category_name": "椅"}, {"collection_num": 1688, "name": "Dance Pouf", "url": "https://image.izhangan.com/nest_9f48c7b90892fbec.jpg", "file_url": "https://image.izhangan.com/nest_9f48c7b90892fbec.jpg", "brand_ename": "Potocco", "height": "1000", "width": "1000", "brand_place_ename": "italy", "category_id": 33, "id": "17969", "category_name": "椅"}, {"collection_num": 693, "name": "Visu - Lounge - Textile", "url": "https://image.izhangan.com/nest_cd6c709f406124d4.jpg", "file_url": "https://image.izhangan.com/nest_cd6c709f406124d4.jpg", "brand_ename": "Muuto", "height": "390", "width": "300", "brand_place_ename": "danmark", "category_id": 33, "id": "17207", "category_name": "椅"}, {"collection_num": 911, "name": "SYLVESTER", "url": "https://image.izhangan.com/nest_46d6cfb441677d7b.jpg", "file_url": "https://image.izhangan.com/nest_46d6cfb441677d7b.jpg", "brand_ename": "Cattelan", "height": "732", "width": "1500", "brand_place_ename": "italy", "category_id": 33, "id": "14502", "category_name": "椅"}, {"collection_num": 1500, "name": "Desire", "url": "https://image.izhangan.com/nest_f26a778b6422130b.jpg", "file_url": "https://image.izhangan.com/nest_f26a778b6422130b.jpg", "brand_ename": "COVET LOUNGE", "height": "1200", "width": "1200", "brand_place_ename": "portugal", "category_id": 33, "id": "13757", "category_name": "椅"}, {"collection_num": 1088, "name": "Equa 2 Stool", "url": "https://image.izhangan.com/nest_dc3909caf957fb69.jpg", "file_url": "https://image.izhangan.com/nest_dc3909caf957fb69.jpg", "brand_ename": "HermanMiller", "height": "780", "width": "840", "brand_place_ename": "america", "category_id": 33, "id": "18576", "category_name": "椅"}, {"collection_num": 1580, "name": "GOSSIP", "url": "https://image.izhangan.com/nest_9661eda261ea7225.jpg", "file_url": "https://image.izhangan.com/nest_9661eda261ea7225.jpg", "brand_ename": "Calligaris", "height": "1280", "width": "1600", "brand_place_ename": "italy", "category_id": 33, "id": "9858", "category_name": "椅"}, {"collection_num": 1197, "name": "Bourbon", "url": "https://image.izhangan.com/nest_4c6407f58049161f.jpg", "file_url": "https://image.izhangan.com/nest_4c6407f58049161f.jpg", "brand_ename": "COVET LOUNGE", "height": "1200", "width": "1200", "brand_place_ename": "portugal", "category_id": 33, "id": "13707", "category_name": "椅"}, {"collection_num": 1393, "name": "LUNA chair", "url": "https://image.izhangan.com/nest_30473dc236fa12cf.jpg", "file_url": "https://image.izhangan.com/nest_30473dc236fa12cf.jpg", "brand_ename": "Plank", "height": "487", "width": "960", "brand_place_ename": "italy", "category_id": 33, "id": "19933", "category_name": "椅"}, {"collection_num": 1502, "name": "Pato Veneer 4 Leg Armchair", "url": "https://image.izhangan.com/nest_37c05a179b8d3e7f.jpg", "file_url": "https://image.izhangan.com/nest_37c05a179b8d3e7f.jpg", "brand_ename": "Fredericia", "height": "675", "width": "1218", "brand_place_ename": "danmark", "category_id": 33, "id": "9869", "category_name": "椅"}, {"collection_num": 1328, "name": "ASTER X", "url": "https://image.izhangan.com/nest_9ac10536671a2e47.jpg", "file_url": "https://image.izhangan.com/nest_9ac10536671a2e47.jpg", "brand_ename": "Poltrona Frau", "height": "450", "width": "900", "brand_place_ename": "italy", "category_id": 33, "id": "10706", "category_name": "椅"}, {"collection_num": 552, "name": "curator black leather director's chair", "url": "https://image.izhangan.com/nest_9d5bce3a8295ac5b.jpg", "file_url": "https://image.izhangan.com/nest_9d5bce3a8295ac5b.jpg", "brand_ename": "Cb2", "height": "800", "width": "800", "brand_place_ename": "america", "category_id": 33, "id": "1201", "category_name": "椅"}, {"collection_num": 925, "name": "ASKIA CHAIR", "url": "https://image.izhangan.com/nest_13566867ddf1bed4.jpg", "file_url": "https://image.izhangan.com/nest_13566867ddf1bed4.jpg", "brand_ename": "Baxter", "height": "1200", "width": "1920", "brand_place_ename": "italy", "category_id": 33, "id": "13069", "category_name": "椅"}, {"collection_num": 1172, "name": "Nonnamaria", "url": "https://image.izhangan.com/nest_e3829198e5f5b0fb.jpg", "file_url": "https://image.izhangan.com/nest_e3829198e5f5b0fb.jpg", "brand_ename": "Flexform", "height": "608", "width": "972", "brand_place_ename": "italy", "category_id": 33, "id": "28387", "category_name": "椅"}, {"collection_num": 1268, "name": "Portfolio", "url": "https://image.izhangan.com/nest_207cf3ea91474b21.jpg", "file_url": "https://image.izhangan.com/nest_207cf3ea91474b21.jpg", "brand_ename": "Molteni", "height": "1080", "width": "1440", "brand_place_ename": "italy", "category_id": 33, "id": "8713", "category_name": "椅"}, {"collection_num": 809, "name": "LOUNGE CHAIR", "url": "https://image.izhangan.com/nest_111bcacacda12efb.jpg", "file_url": "https://image.izhangan.com/nest_111bcacacda12efb.jpg", "brand_ename": "Dedon", "height": "1266", "width": "1920", "brand_place_ename": "germany", "category_id": 33, "id": "18217", "category_name": "椅"}, {"collection_num": 1272, "name": "LOVELY | CHAIR", "url": "https://image.izhangan.com/nest_562f69606a6ee0cc.jpg", "file_url": "https://image.izhangan.com/nest_562f69606a6ee0cc.jpg", "brand_ename": "KOKET", "height": "450", "width": "1200", "brand_place_ename": "america", "category_id": 33, "id": "12731", "category_name": "椅"}, {"collection_num": 1339, "name": "ILT CHAIR", "url": "https://image.izhangan.com/nest_ddf07805d4407478.jpg", "file_url": "https://image.izhangan.com/nest_ddf07805d4407478.jpg", "brand_ename": "Woodmark", "height": "625", "width": "1000", "brand_place_ename": "australia", "category_id": 33, "id": "121730", "category_name": "椅"}, {"collection_num": 1925, "name": "Nanook", "url": "https://image.izhangan.com/nest_ced938c2b35d82aa.jpg", "file_url": "https://image.izhangan.com/nest_ced938c2b35d82aa.jpg", "brand_ename": "COVET LOUNGE", "height": "1200", "width": "1200", "brand_place_ename": "portugal", "category_id": 33, "id": "13983", "category_name": "椅"}, {"collection_num": 1196, "name": "1919", "url": "https://image.izhangan.com/nest_49d1138b6086f419.jpg", "file_url": "https://image.izhangan.com/nest_49d1138b6086f419.jpg", "brand_ename": "Poltrona Frau", "height": "450", "width": "900", "brand_place_ename": "italy", "category_id": 33, "id": "10691", "category_name": "椅"}, {"collection_num": 1066, "name": "Low Lounger - Swivel", "url": "https://image.izhangan.com/nest_5d7ae0d490742518.jpg", "file_url": "https://image.izhangan.com/nest_5d7ae0d490742518.jpg", "brand_ename": "Barcelona design", "height": "546", "width": "779", "brand_place_ename": "spain", "category_id": 33, "id": "16093", "category_name": "椅"}, {"collection_num": 1192, "name": "Oyster High", "url": "https://image.izhangan.com/nest_a1bcdfe8995fe74b.jpg", "file_url": "https://image.izhangan.com/nest_a1bcdfe8995fe74b.jpg", "brand_ename": "Offecct", "height": "800", "width": "659", "brand_place_ename": "sweden", "category_id": 33, "id": "11345", "category_name": "椅"}, {"collection_num": 1509, "name": "Osaka椅", "url": "https://image.izhangan.com/nest_2e6b6c004eaea0a2.jpg", "file_url": "https://image.izhangan.com/nest_2e6b6c004eaea0a2.jpg", "brand_ename": "BoConcept", "height": "1572", "width": "2000", "brand_place_ename": "danmark", "category_id": 33, "id": "7753", "category_name": "椅"}], "file_width": "1200"}